{
  "indexes": [
    {
      "collectionGroup": "reviews",
      "queryScope": "COLLECTION",
      "fields": [
        { "fieldPath": "status", "order": "ASCENDING" },
        { "fieldPath": "source", "order": "ASCENDING" },
        { "fieldPath": "created_at", "order": "DESCENDING" }
      ]
    },
    {
      "collectionGroup": "runs",
      "queryScope": "COLLECTION",
      "fields": [
        { "fieldPath": "host", "order": "ASCENDING" },
        { "fieldPath": "finished_at", "order": "ASCENDING" }
      ]
    },
    {
      "collectionGroup": "runs",
      "queryScope": "COLLECTION_GROUP",
      "fields": [
        { "fieldPath": "project_id", "order": "ASCENDING" },
        { "fieldPath": "started_at", "order": "DESCENDING" }
      ]
    }
  ],
  "fieldOverrides": []
}
